LICENSE.txt
MANIFEST.in
README.rst
setup.cfg
setup.py
testtrackpro.py
docs/Makefile
docs/conf.py
docs/index.rst
testtrackpro.egg-info/PKG-INFO
testtrackpro.egg-info/SOURCES.txt
testtrackpro.egg-info/dependency_links.txt
testtrackpro.egg-info/requires.txt
testtrackpro.egg-info/top_level.txt