Metadata-Version: 1.1
Name: testtrackpro
Version: 1.0.1
Summary: Python interface to TestTrackPro SOAP API
Home-page: https://github.com/dougn/python-testtrackpro/
Author: Doug Napoleone
Author-email: doug.napoleone+testtrackpro@gmail.com
License: BSD
Keywords: testtrack,testtrackpro,soap,suds
Platform: UNKNOWN
Classifier: Development Status :: 5 - Production/Stable
Classifier: Programming Language :: Python
Classifier: Programming Language :: Python :: 2.6
Classifier: Programming Language :: Python :: 2.7
Classifier: Intended Audience :: Developers
Classifier: Intended Audience :: System Administrators
Classifier: License :: OSI Approved :: BSD License
Classifier: Topic :: Internet :: WWW/HTTP
Classifier: Topic :: Utilities
Classifier: Topic :: Software Development :: Libraries :: Python Modules
